{"id":"i~ae2fc~ec2placeholder.part.base~0","imageFilePath":"item/ae2fc/ec2placeholder.part.base~0.png","internalName":"ec2placeholder.part.base","itemDamage":0,"itemId":10839,"localizedName":"item.ec2placeholder.part.base.name","maxDamage":0,"maxStackSize":64,"modId":"ae2fc","nbt":"","tooltip":"item.ec2placeholder.part.base.name (#10839/0)\nae2fc:ec2placeholder.part.base\nExtra Cells Placeholder for:\nitem.part_fluid_export\nPut in your inventory to get a replacement.\nIt will disappear if no replacement was found.\nReport missing conversions on the Github.","unlocalizedName":"item.ec2placeholder.part.base"}