{"id":"i~bartworks~gt.bwMetaGeneratedcapsuleMolten~10105","imageFilePath":"item/bartworks/gt.bwMetaGeneratedcapsuleMolten~10105.png","internalName":"gt.bwMetaGeneratedcapsuleMolten","itemDamage":10105,"itemId":10614,"localizedName":"熔融光素胶囊","maxDamage":0,"maxStackSize":64,"modId":"bartworks","nbt":"","tooltip":"熔融光素胶囊 (#10614/10105)\nbartworks:gt.bwMetaGeneratedcapsuleMolten\n((SnFe)₄(CuAg₄)₂(Al??)₂(PO₄)₄₂)₁₈Ag₈Su₄\n由 Good Generator via BartWorks 添加","unlocalizedName":"gt.bwMetaGeneratedcapsuleMolten.10105"}