{"id":"i~bartworks~bw.werkstoffblockscasingadvanced.01~10096","imageFilePath":"item/bartworks/bw.werkstoffblockscasingadvanced.01~10096.png","internalName":"bw.werkstoffblockscasingadvanced.01","itemDamage":10096,"itemId":3660,"localizedName":"强化MAR-M200特种钢机械方块","maxDamage":0,"maxStackSize":64,"modId":"bartworks","nbt":"","tooltip":"强化MAR-M200特种钢机械方块 (#3660/10096)\nbartworks:bw.werkstoffblockscasingadvanced.01\nNb₂Cr₉Al₅Ti₂Co₁₀W₁₃Ni₁₈\n由 Good Generator via BartWorks 添加","unlocalizedName":"bw.werkstoffblockscasingadvanced.01.10096"}