{"id":"i~GraviSuite~advNanoChestPlate~1~X5ilYeiyNfOweUqaEfDSEw\u003d\u003d","imageFilePath":"item/GraviSuite/advNanoChestPlate~1~X5ilYeiyNfOweUqaEfDSEw\u003d\u003d.png","internalName":"advNanoChestPlate","itemDamage":1,"itemId":10123,"localizedName":"进阶纳米重力胸甲","maxDamage":27,"maxStackSize":1,"modId":"GraviSuite","nbt":"{charge:3000000.0d}","tooltip":"进阶纳米重力胸甲 (#10123)\nGraviSuite:advNanoChestPlate\n喷气引擎: 关\n悬停模式: 关\nDurability: 26 / 27\nProvides full hazmat protection.\n保护: 8\n耐久: 26/27","unlocalizedName":"item.advNanoChestPlate"}