{"id":"i~gregtech~gt.blockmachines~32017","imageFilePath":"item/gregtech/gt.blockmachines~32017.png","internalName":"gt.blockmachines","itemDamage":32017,"itemId":2196,"localizedName":"超级热交换机","maxDamage":0,"maxStackSize":64,"modId":"gregtech","nbt":"","tooltip":"超级热交换机 (#2196/32017)\ngregtech:gt.blockmachines\n机器类型：热交换机/等离子热交换机\n超级热交换机的控制器方块\n接受热流体如岩浆、热冷却液或等离子体.\n输出超临界蒸汽/过热蒸汽/蒸汽.\n请参阅NEI获取更多信息.\n请参考StructureLib全息投影，构建主体结构\n-----------------------------------------\n按住 [LSHIFT] 以显示结构指导\n由 Good Generator 添加","unlocalizedName":"gt.blockmachines.extremeheatexchanger"}