{"id":"i~gregtech~gt.blockmachines~19030","imageFilePath":"item/gregtech/gt.blockmachines~19030.png","internalName":"gt.blockmachines","itemDamage":19030,"itemId":2196,"localizedName":"热能饕餮","maxDamage":0,"maxStackSize":64,"modId":"gregtech","nbt":"","tooltip":"热能饕餮 (#2196/19030)\ngregtech:gt.blockmachines\n机器类型: 真空冷冻机\n热能饕餮的控制器方块\n 又到了白色相簿的季节.\n它贪婪地吞噬着热量.\n但总的来说仍是一台冷冻机, 而且工作得不错.\n提高输入功率的同时会提高运行效率.\n使用螺丝刀切换模式.\n ----- 高速模式 -----\n运行效率直接降低处理耗时.\n1024x 并行.\n ----- 饕餮模式 -----\n运行效率降低EU消耗.\n几乎无限的并行.\n ----- 无线模式 -----\n在控制器内放入充能超立方体以切换至无线模式.\n直接在无线EU网络中消耗所需的能量.\n处理时间固定为6.4s .\n-----------------------------------------\n结构太复杂了！\n请参考StructureLib全息投影，构建主体结构\n按住 [LSHIFT] 以显示结构指导\n添加模组: Twist Space Technology","unlocalizedName":"gt.blockmachines.namethermalenergydevourer"}