{"id":"i~gregtech~gt.blockmachines~15331","imageFilePath":"item/gregtech/gt.blockmachines~15331.png","internalName":"gt.blockmachines","itemDamage":15331,"itemId":2442,"localizedName":"研究站","maxDamage":0,"maxStackSize":64,"modId":"gregtech","nbt":"","tooltip":"研究站 (#2442/15331)\n机器类型：研究站,扫描仪\n用于扫描物品，生成装配线配方闪存\n需要为其提供算力\n在完成闪存写入之前不会消耗物品\n使用螺丝刀切换模式.\n扫描模式所需计算遵循公式：\n配方持续时间（tick）* (2 ^ (配方电压等级 - 1))\n支持TecTech多A能源仓与激光仓!\n-----------------------------------------\n按住 [LSHIFT] 以显示结构指导","unlocalizedName":"gt.blockmachines.multimachine.em.research"}