{"id":"i~gregtech~gt.blockmachines~2105","imageFilePath":"item/gregtech/gt.blockmachines~2105.png","internalName":"gt.blockmachines","itemDamage":2105,"itemId":2196,"localizedName":"极限内燃引擎","maxDamage":0,"maxStackSize":64,"modId":"gregtech","nbt":"","tooltip":"极限内燃引擎 (#2196/2105)\ngregtech:gt.blockmachines\n机器类型：内燃发电机\n极限内燃引擎的控制器方块\n提供高热值燃油与8000升/小时的润滑油以运行\n提供40升/秒的液氧进行增压(可选)\n默认：燃料效率100%，输出功率10900EU/t\n增压：燃料效率150%，输出功率32700EU/t\n需要等待其达到300%才能全功率输出\n每秒产生3840点污染\n-----------------------------------------\n按住 [LSHIFT] 以显示结构指导\n由 Gregtech 添加","unlocalizedName":"gt.blockmachines.multimachine.extremedieselengine"}