{"id":"i~gregtech~gt.blockmachines~14001","imageFilePath":"item/gregtech/gt.blockmachines~14001.png","internalName":"gt.blockmachines","itemDamage":14001,"itemId":2442,"localizedName":"戴森球地面单元","maxDamage":0,"maxStackSize":64,"modId":"gregtech","nbt":"","tooltip":"戴森球地面单元 (#2442/14001)\n机器类型：戴森球\n9号吗？不完全是。\n在输入总线中放入戴森球模块，以将其发射至相邻的恒星。\n每个模块输出10,000,000*DEU/t，至多10000个\n每小时，模块中 I * (2 * 0.066) / (exp(-0.00005 * (I - 1)) + exp(0.00003 * C))  个被摧毁。译者注：exp(x)\u003de^x\nC算力/s，I初始模块数量，D维度相关因子（数值详见任务页）\n每小时消耗3,600,000L极寒之凛冰\n手持搋子右键，可以取出尽可能多的模块放入物品栏中\nShift+右键会将剩余模块扔在地上\n支持TecTech多A能源仓与激光仓!\n-----------------------------------------\n按住 [LSHIFT] 以显示结构指导\n添加者：: glowredman","unlocalizedName":"gt.blockmachines.dysonswarm"}