{"id":"i~gregtech~gt.blockmachines~12675","imageFilePath":"item/gregtech/gt.blockmachines~12675.png","internalName":"gt.blockmachines","itemDamage":12675,"itemId":2196,"localizedName":"线缆二极管 12A UEV","maxDamage":0,"maxStackSize":64,"modId":"gregtech","nbt":"","tooltip":"线缆二极管 12A UEV (#2196/12675)\ngregtech:gt.blockmachines\n一种简单的二极管,只允许能量流向一个方向.\n电压：8,388,608\n输入电流：12\n输出电流：12\n添加者：bartimaeusnek,模组：BartWorks\n输入电压：8,388,608 (UEV)\n输出电压：8,388,608 (UEV)\n电流：12\n电能缓存：419,430,912 EU","unlocalizedName":"gt.blockmachines.diode12auev"}