{"id":"i~gregtech~gt.blockmachines~10506","imageFilePath":"item/gregtech/gt.blockmachines~10506.png","internalName":"gt.blockmachines","itemDamage":10506,"itemId":2442,"localizedName":"高能粒子辐射激发源室","maxDamage":0,"maxStackSize":64,"modId":"gregtech","nbt":"","tooltip":"高能粒子辐射激发源室 (#2442/10506)\n机器类型：粒子源\n生成粒子束\n使用便携式扫描仪右键来获取多方块输入输出信息\n-----------------------------------------\nNEI显示最低EU/t需求、光束聚焦、光束比率以及最大光束能量\n所有配方持续一秒钟\n当运行功率增加时，该上限会渐近地趋近\n-----------------------------------------\n每种粒子类型都有其最大粒子能量\nα粒子：8000keV\n质子：15000keV\n中子：15000keV\n电子：5000keV\n-----------------------------------------\n每个源输入都有一个关联的能量比率\n铀-238粉：999\n锎粉：999\n钨杆：0.1\n长LaB6杆：0.3\n-----------------------------------------\n实际光束能量 \u003d min(最大粒子能量, aeV)\n其中 aeV \u003d 最大光束能量 * (1 - 1.001^(能量比率 * (所需EU/t - 提供EU/t)))\n简而言之，粒子束的能量上限为最大粒子能量。\n任何单一配方最多只能提供其自身的最大光束能量\n-----------------------------------------\n按住 [LSHIFT] 以显示结构指导","unlocalizedName":"gt.blockmachines.source_chamber"}