{"id":"i~gregtech~gt.blockmachines~14010","imageFilePath":"item/gregtech/gt.blockmachines~14010.png","internalName":"gt.blockmachines","itemDamage":14010,"itemId":2196,"localizedName":"太空钻机模块MK-I","maxDamage":0,"maxStackSize":64,"modId":"gregtech","nbt":"","tooltip":"太空钻机模块MK-I (#2196/14010)\ngregtech:gt.blockmachines\n机器类型：太空电梯模块\n将太空钻机功能添加到太空电梯\n吸干气态行星从未如此简单\n直接从太空电梯接收能量；不使用能源仓\n设定的行星和气体类型决定了输出的流体\n锁定输出仓即可防止溢出销毁\n需要MK-II或更高等级的加速轨道\n-----------------------------------------\n按住 [LSHIFT] 以显示结构指导\n由 GTNH-Intergalactic 添加\n电能缓存：640,032,000 EU","unlocalizedName":"gt.blockmachines.projectmodulepumpt1"}