{"id":"i~gregtech~gt.blockmachines~31021","imageFilePath":"item/gregtech/gt.blockmachines~31021.png","internalName":"gt.blockmachines","itemDamage":31021,"itemId":2196,"localizedName":"丹格特蒸馏厂","maxDamage":0,"maxStackSize":64,"modId":"gregtech","nbt":"","tooltip":"丹格特蒸馏厂 (#2196/31021)\ngregtech:gt.blockmachines\n机器类型：蒸馏室,蒸馏塔\n工业蒸馏塔的控制器方块\n在蒸馏室模式下，减少85%能耗\n在蒸馏塔/蒸馏室模式下，分别快250%/100%\n手持螺丝刀右键控制器方块以切换模式\n最大并行取决于机器的等级和模式\n蒸馏塔模式：T1\u003d4，T2\u003d12\n蒸馏室模式：蒸馏塔等级*(4*电压等级)\n蒸馏室模式需要全高度结构\n每秒产生480点污染\n-----------------------------------------\n按住 [LSHIFT] 以显示结构指导\n添加者：Alkalus - [GT++]","unlocalizedName":"gt.blockmachines.multimachine.adv.distillationtower"}