{"id":"i~gregtech~gt.blockmachines~850","imageFilePath":"item/gregtech/gt.blockmachines~850.png","internalName":"gt.blockmachines","itemDamage":850,"itemId":2442,"localizedName":"工业洗矿厂","maxDamage":0,"maxStackSize":64,"modId":"gregtech","nbt":"","tooltip":"工业洗矿厂 (#2442/850)\n机器类型：洗矿机，简易洗矿池，化学浸洗机；机器简称：OWP\n每个电压等级提供4并行\n500%运行速度\n能量消耗：100%\n可用螺丝刀进行配置，使用简单洗矿或化学浸洗配方\n始终需要装满水的输入仓以填充结构\n需要装满水\n会自动从输入仓抽水填充结构\n每秒产生100点污染\n-----------------------------------------\n按住 [LSHIFT] 以显示结构指导","unlocalizedName":"gt.blockmachines.industrialwashplant.controller.tier.single"}