{"id":"i~TConstruct~travelGoggles~0~WM4RGdu9O2miUgLtZVrjqA\u003d\u003d","imageFilePath":"item/TConstruct/travelGoggles~0~WM4RGdu9O2miUgLtZVrjqA\u003d\u003d.png","internalName":"travelGoggles","itemDamage":0,"itemId":4653,"localizedName":"旅行者护目镜","maxDamage":1035,"maxStackSize":1,"modId":"TConstruct","nbt":"{TinkerArmor:{BaseDurability:1035L,BaseDefense:0.0d,Built:1L,MaxDefense:4.0d,Damage:0L,BonusDurability:0L,Modifiers:3L,TotalDurability:1035L,ModDurability:0.0d,DamageReduction:0.0d,Broken:0L}}","tooltip":"旅行者护目镜 (#4653)\nTConstruct:travelGoggles\n能力: 变焦Z\n能力: 切换工具栏NONE\n保护: 4%\n保护: 2\n耐久: 1035/1035","unlocalizedName":"item.tconstruct.travelgoggles"}