{"id":"i~TGregworks~tGregToolPartScytheHead~1535~QfGt2htpPGa_8lOd1zdRLg\u003d\u003d","imageFilePath":"item/TGregworks/tGregToolPartScytheHead~1535~QfGt2htpPGa_8lOd1zdRLg\u003d\u003d.png","internalName":"tGregToolPartScytheHead","itemDamage":1535,"itemId":7679,"localizedName":"山铜 镰刀刀刃","maxDamage":0,"maxStackSize":64,"modId":"TGregworks","nbt":"{material:\"Orichalcum\"}","tooltip":"山铜 镰刀刀刃 (#7679/1535)\nTGregworks:tGregToolPartScytheHead\n耐久:15360\n使用速度:32\n攻击力:0.5 心\n\n可被替换","unlocalizedName":"Orichalcum"}