{"id":"i~TGregworks~tGregToolPartLargeSwordBlade~1621~g-9X8h-XPjGaUGB1cEYcOg\u003d\u003d","imageFilePath":"item/TGregworks/tGregToolPartLargeSwordBlade~1621~g-9X8h-XPjGaUGB1cEYcOg\u003d\u003d.png","internalName":"tGregToolPartLargeSwordBlade","itemDamage":1621,"itemId":7682,"localizedName":"紫水晶 宽剑刃","maxDamage":0,"maxStackSize":64,"modId":"TGregworks","nbt":"{material:\"Amethyst\"}","tooltip":"紫水晶 宽剑刃 (#7682/1621)\nTGregworks:tGregToolPartLargeSwordBlade\n攻击力:1.5 心\n耐久:192\n\n可被替换","unlocalizedName":"Amethyst"}