{"id":"i~TGregworks~tGregToolPartCrossbowBody~1557~DOYwWNCtMd-ScdGu0xUoBg\u003d\u003d","imageFilePath":"item/TGregworks/tGregToolPartCrossbowBody~1557~DOYwWNCtMd-ScdGu0xUoBg\u003d\u003d.png","internalName":"tGregToolPartCrossbowBody","itemDamage":1557,"itemId":7688,"localizedName":"石墨烯 弩身","maxDamage":0,"maxStackSize":64,"modId":"TGregworks","nbt":"{material:\"Graphene\"}","tooltip":"石墨烯 弩身 (#7688/1557)\nTGregworks:tGregToolPartCrossbowBody\n耐久:24\n拉弓速度:0.5s\n箭矢速度:0.5\n\n可被替换","unlocalizedName":"Graphene"}