{"id":"i~TGregworks~tGregToolPartSwordBlade~1721~aEyyyBjZMIaleX0aSUYJsg\u003d\u003d","imageFilePath":"item/TGregworks/tGregToolPartSwordBlade~1721~aEyyyBjZMIaleX0aSUYJsg\u003d\u003d.png","internalName":"tGregToolPartSwordBlade","itemDamage":1721,"itemId":7670,"localizedName":"精金合金 剑刃","maxDamage":0,"maxStackSize":64,"modId":"TGregworks","nbt":"{material:\"AdamantiumAlloy\"}","tooltip":"精金合金 剑刃 (#7670/1721)\nTGregworks:tGregToolPartSwordBlade\n攻击力:2.5 心\n耐久:76800\n\n可被替换","unlocalizedName":"Adamantium Alloy"}