{"id":"i~TGregworks~tGregToolPartScytheHead~1577~SrvN3cr6PeyvNqjA02AtUw\u003d\u003d","imageFilePath":"item/TGregworks/tGregToolPartScytheHead~1577~SrvN3cr6PeyvNqjA02AtUw\u003d\u003d.png","internalName":"tGregToolPartScytheHead","itemDamage":1577,"itemId":7679,"localizedName":"超能硅岩 镰刀刀刃","maxDamage":0,"maxStackSize":64,"modId":"TGregworks","nbt":"{material:\"Naquadria\"}","tooltip":"超能硅岩 镰刀刀刃 (#7679/1577)\nTGregworks:tGregToolPartScytheHead\n耐久:384\n使用速度:1\n攻击力:2 心\n\n可被替换","unlocalizedName":"Naquadria"}