{"id":"i~TGregworks~tGregToolPartChiselHead~1627~eZc4cbK5MsSyYAT3p8vsZQ\u003d\u003d","imageFilePath":"item/TGregworks/tGregToolPartChiselHead~1627~eZc4cbK5MsSyYAT3p8vsZQ\u003d\u003d.png","internalName":"tGregToolPartChiselHead","itemDamage":1627,"itemId":7678,"localizedName":"标准纯银 凿刃","maxDamage":0,"maxStackSize":64,"modId":"TGregworks","nbt":"{material:\"SterlingSilver\"}","tooltip":"标准纯银 凿刃 (#7678/1627)\nTGregworks:tGregToolPartChiselHead\n耐久:96\n使用速度:13\n\n可被替换","unlocalizedName":"Sterling Silver"}