{"id":"i~TGregworks~tGregToolPartSwordBlade~1664~grs1UzMGM_-wDni7z0ZKTw\u003d\u003d","imageFilePath":"item/TGregworks/tGregToolPartSwordBlade~1664~grs1UzMGM_-wDni7z0ZKTw\u003d\u003d.png","internalName":"tGregToolPartSwordBlade","itemDamage":1664,"itemId":7670,"localizedName":"丁苯橡胶 剑刃","maxDamage":0,"maxStackSize":64,"modId":"TGregworks","nbt":"{material:\"StyreneButadieneRubber\"}","tooltip":"丁苯橡胶 剑刃 (#7670/1664)\nTGregworks:tGregToolPartSwordBlade\n攻击力:0.5 心\n耐久:96\n\n可被替换","unlocalizedName":"Styrene-Butadiene Rubber"}