{"id":"i~TGregworks~tGregToolPartArrowHead~1545~mpIjKZIjPBqgJSYUWwN8-Q\u003d\u003d","imageFilePath":"item/TGregworks/tGregToolPartArrowHead~1545~mpIjKZIjPBqgJSYUWwN8-Q\u003d\u003d.png","internalName":"tGregToolPartArrowHead","itemDamage":1545,"itemId":7685,"localizedName":"暗影秘银 箭头","maxDamage":0,"maxStackSize":64,"modId":"TGregworks","nbt":"{material:\"Ceruclase\"}","tooltip":"暗影秘银 箭头 (#7685/1545)\nTGregworks:tGregToolPartArrowHead\n攻击力:1 心\n耐久:960\n损坏几率: 90%\n重量:9.8\n\n可被替换","unlocalizedName":"Ceruclase"}