{"id":"i~TGregworks~tGregToolPartLargePlate~1611~C9UeLHN2OpSJ40tUdX_g8g\u003d\u003d","imageFilePath":"item/TGregworks/tGregToolPartLargePlate~1611~C9UeLHN2OpSJ40tUdX_g8g\u003d\u003d.png","internalName":"tGregToolPartLargePlate","itemDamage":1611,"itemId":7669,"localizedName":"蓝宝石 大板","maxDamage":0,"maxStackSize":64,"modId":"TGregworks","nbt":"{material:\"Sapphire\"}","tooltip":"蓝宝石 大板 (#7669/1611)\nTGregworks:tGregToolPartLargePlate\n耐久:192\n采掘速度:7\n攻击力:1 心\n\n可被替换","unlocalizedName":"Sapphire"}