{"id":"i~TGregworks~tGregToolPartCrossbowBody~1616~teZ-q8AxORO8VUueQvtB5w\u003d\u003d","imageFilePath":"item/TGregworks/tGregToolPartCrossbowBody~1616~teZ-q8AxORO8VUueQvtB5w\u003d\u003d.png","internalName":"tGregToolPartCrossbowBody","itemDamage":1616,"itemId":7688,"localizedName":"哈氏合金 弩身","maxDamage":0,"maxStackSize":64,"modId":"TGregworks","nbt":"{material:\"Ultimet\"}","tooltip":"哈氏合金 弩身 (#7688/1616)\nTGregworks:tGregToolPartCrossbowBody\n耐久:1536\n拉弓速度:2s\n箭矢速度:3.5\n\n可被替换","unlocalizedName":"Ultimet"}