{"id":"i~universalsingularities~universal.draconicEvolution.singularity~0","imageFilePath":"item/universalsingularities/universal.draconicEvolution.singularity~0.png","internalName":"universal.draconicEvolution.singularity","itemDamage":0,"itemId":10022,"localizedName":"龙奇点","maxDamage":0,"maxStackSize":64,"modId":"universalsingularities","nbt":"","tooltip":"龙奇点 (#10022/0)\nuniversalsingularities:universal.draconicEvolution.singularity","unlocalizedName":"item.universalSingularities.draconicEvolution.draconium"}